urlwait2.py
urlwait2-0.3.dist-info/METADATA
urlwait2-0.3.dist-info/RECORD
urlwait2-0.3.dist-info/WHEEL
urlwait2-0.3.dist-info/entry_points.txt
urlwait2-0.3.dist-info/top_level.txt
