Metadata-Version: 2.1
Name: urlwait2
Version: 0.3
Summary: wait for http url to return expected status code
Home-page: https://github.com/Fak3/urlwait2
Author: Roman Evstifeev
Author-email: someuniquename@gmail.com
License: MIT
Platform: UNKNOWN
Classifier: Development Status :: 4 - Beta
Classifier: Intended Audience :: Developers
Classifier: License :: OSI Approved :: MIT License
Classifier: Operating System :: Microsoft :: Windows
Classifier: Operating System :: OS Independent
Classifier: Operating System :: POSIX :: Linux
Classifier: Operating System :: MacOS :: MacOS X
Classifier: Operating System :: Android
Classifier: Programming Language :: Python :: 3
Classifier: Topic :: Software Development
Classifier: Topic :: Utilities
Requires-Dist: click
Requires-Dist: requests
